mpltw/TaipeiSansTCBeta-Regular.ttf
mpltw/__init__.py
mpltw-0.1.0.dist-info/LICENSE
mpltw-0.1.0.dist-info/METADATA
mpltw-0.1.0.dist-info/WHEEL
mpltw-0.1.0.dist-info/top_level.txt
mpltw-0.1.0.dist-info/RECORD
