Metadata-Version: 2.1
Name: mpltw
Version: 0.1.0
Summary: Using matplotlib with tranditional Chinese word more easily.
Home-page: https://gitlab.com/scku208/matplotlib-taiwan-font
Author: scku208
Author-email: scku208@gmail.com
License: MIT
Download-URL: https://gitlab.com/scku208/matplotlib-taiwan-font/-/archive/master/matplotlib-taiwan-font-master.zip
Keywords: matplotlib,tranditional,Chinese
Platform: UNKNOWN
Classifier: Programming Language :: Python :: 3
Classifier: Programming Language :: Python :: 3.4
Classifier: Programming Language :: Python :: 3.5
Classifier: Programming Language :: Python :: 3.6
Classifier: Programming Language :: Python :: 3.7
Classifier: Programming Language :: Python :: 3.8
Classifier: Programming Language :: Python :: 3.9
Requires-Dist: matplotlib
